<?xml version="1.0" encoding="UTF-8"?>
<!DOCTYPE plist PUBLIC "-//Apple//DTD PLIST 1.0//EN" "http://www.apple.com/DTDs/PropertyList-1.0.dtd"/>

<plist version="1.0">
    <dict>
        <key>ROOT</key>
        <array>
            <dict>
                <key>id</key>
                <string>5414</string>
                <key>className</key>
                <string>PTModelObjectAssetPath</string>
                <key>Name</key>
                <dict>
                    <key>value</key>
                    <string>Path</string>
                </dict>
                <key>Position</key>
                <dict>
                    <key>value</key>
                    <string>{1049.467,485.529}</string>
                </dict>
                <key>Scale</key>
                <dict>
                    <key>value</key>
                    <string>{1.000,1.000}</string>
                </dict>
                <key>Hidden</key>
                <dict>
                    <key>visible</key>
                    <string>0</string>
                </dict>
                <key>Locked</key>
                <dict>
                    <key>visible</key>
                    <string>0</string>
                </dict>
                <key>Speed</key>
                <dict>
                    <key>value</key>
                    <string>10.000000</string>
                </dict>
                <key>Play Mode</key>
                <dict>
                    <key>selectedStringValue</key>
                    <string>kPlayModePingPong</string>
                </dict>
                <key>Affected Asset</key>
                <dict>
                    <key>selectedStringValue</key>
                    <string>kAll</string>
                </dict>
                <key>zDepth</key>
                <string>501</string>
                <key>points</key>
                <array>
                    <string>{0.000,-74.000}</string>
                    <string>{-3.016,-108.566}</string>
                    <string>{36.189,-337.759}</string>
                    <string>{250.304,30.157}</string>
                    <string>{322.681,-322.681}</string>
                    <string>{-247.288,-334.744}</string>
                </array>
            </dict>
            <dict>
                <key>id</key>
                <string>7089</string>
                <key>className</key>
                <string>PTModelObjectAssetPath</string>
                <key>Name</key>
                <dict>
                    <key>value</key>
                    <string>Path</string>
                </dict>
                <key>Position</key>
                <dict>
                    <key>value</key>
                    <string>{13945.286,580.062}</string>
                </dict>
                <key>Scale</key>
                <dict>
                    <key>value</key>
                    <string>{1.000,1.000}</string>
                </dict>
                <key>Hidden</key>
                <dict>
                    <key>visible</key>
                    <string>0</string>
                </dict>
                <key>Locked</key>
                <dict>
                    <key>visible</key>
                    <string>0</string>
                </dict>
                <key>Search Radius</key>
                <dict>
                    <key>value</key>
                    <string>40.000000</string>
                </dict>
                <key>Speed</key>
                <dict>
                    <key>value</key>
                    <string>40.000000</string>
                </dict>
                <key>Play Mode</key>
                <dict>
                    <key>selectedStringValue</key>
                    <string>kPlayModePingPong</string>
                </dict>
                <key>Affected Asset</key>
                <dict>
                    <key>selectedStringValue</key>
                    <string>kAll</string>
                </dict>
                <key>zDepth</key>
                <string>505</string>
                <key>points</key>
                <array>
                    <string>{1.133,-257.176}</string>
                    <string>{-0.941,-376.575}</string>
                </array>
            </dict>
        </array>
    </dict>
</plist>
